throttled/__init__.py
throttled/constants.py
throttled/exceptions.py
throttled/py.typed
throttled/throttled.py
throttled/types.py
throttled/utils.py
throttled/asyncio/__init__.py
throttled/asyncio/throttled.py
throttled/asyncio/rate_limiter/__init__.py
throttled/asyncio/rate_limiter/base.py
throttled/asyncio/rate_limiter/fixed_window.py
throttled/asyncio/rate_limiter/gcra.py
throttled/asyncio/rate_limiter/leaking_bucket.py
throttled/asyncio/rate_limiter/sliding_window.py
throttled/asyncio/rate_limiter/token_bucket.py
throttled/asyncio/store/__init__.py
throttled/asyncio/store/base.py
throttled/asyncio/store/memory.py
throttled/asyncio/store/redis.py
throttled/rate_limiter/__init__.py
throttled/rate_limiter/base.py
throttled/rate_limiter/fixed_window.py
throttled/rate_limiter/gcra.py
throttled/rate_limiter/leaking_bucket.py
throttled/rate_limiter/sliding_window.py
throttled/rate_limiter/token_bucket.py
throttled/rate_limiter/lua/fixed_window.lua
throttled/rate_limiter/lua/gcra.lua
throttled/rate_limiter/lua/gcra_peek.lua
throttled/rate_limiter/lua/leaking_bucket.lua
throttled/rate_limiter/lua/sliding_window.lua
throttled/rate_limiter/lua/token_bucket.lua
throttled/store/__init__.py
throttled/store/base.py
throttled/store/memory.py
throttled/store/redis.py
throttled/store/redis_pool.py
throttled_py-3.1.0.dist-info/METADATA
throttled_py-3.1.0.dist-info/WHEEL
throttled_py-3.1.0.dist-info/licenses/LICENSE
throttled_py-3.1.0.dist-info/RECORD
