Metadata-Version: 2.4
Name: throttled-py
Version: 3.1.0
Summary: 🔧 High-performance Python rate limiting library with multiple algorithms (Fixed Window, Sliding Window, Token Bucket, Leaky Bucket & GCRA) and storage backends (Redis, In-Memory).
Project-URL: Homepage, https://github.com/ZhuoZhuoCrayon/throttled-py
Project-URL: Repository, https://github.com/ZhuoZhuoCrayon/throttled-py
Project-URL: Documentation, https://throttled-py.readthedocs.io
Project-URL: Changes, https://github.com/ZhuoZhuoCrayon/throttled-py/releases
Project-URL: Bug Tracker, https://github.com/ZhuoZhuoCrayon/throttled-py/issues
Author-email: ZhuoZhuoCrayon <crayon.ccxx@gmail.com>
License: MIT
License-File: LICENSE
Classifier: Development Status :: 5 - Production/Stable
Classifier: Intended Audience :: Developers
Classifier: License :: OSI Approved :: MIT License
Classifier: Operating System :: MacOS
Classifier: Operating System :: OS Independent
Classifier: Operating System :: POSIX :: Linux
Classifier: Programming Language :: Python :: 3.10
Classifier: Programming Language :: Python :: 3.11
Classifier: Programming Language :: Python :: 3.12
Classifier: Programming Language :: Python :: 3.13
Classifier: Programming Language :: Python :: 3.14
Classifier: Programming Language :: Python :: Implementation :: PyPy
Classifier: Topic :: Software Development :: Libraries :: Python Modules
Requires-Python: >=3.10
Provides-Extra: memory
Provides-Extra: redis
Requires-Dist: redis!=4.5.2,!=4.5.3,<8.0.0,>3; extra == 'redis'
